audlib/__init__.py
audlib/enhance.py
audlib/noise.py
audlib/pitch.py
audlib/plot.py
audlib/quickstart.py
audlib/vad.py
audlib/asr/__init__.py
audlib/asr/util.py
audlib/cfg/audpipe/extract.ini
audlib/cli/__init__.py
audlib/cli/audpipe.py
audlib/cli/filetypes.py
audlib/cli/utils.py
audlib/data/__init__.py
audlib/data/arctic.py
audlib/data/asvspoof.py
audlib/data/avspoof.py
audlib/data/dataset.py
audlib/data/datatype.py
audlib/data/enhance.py
audlib/data/esc50.py
audlib/data/librispeech.py
audlib/data/rats.py
audlib/data/timit.py
audlib/data/vctk.py
audlib/data/wsj.py
audlib/eval/__init__.py
audlib/eval/enhance.py
audlib/io/__init__.py
audlib/io/audio.py
audlib/io/batch.py
audlib/io/sphinx.py
audlib/misc/cmudict-0.7b
audlib/misc/wsj.filler
audlib/misc/wsj.phone
audlib/nn/__init__.py
audlib/nn/nn.py
audlib/nn/rnn.py
audlib/nn/signal.py
audlib/nn/transform.py
audlib/nn/util.py
audlib/samples/COPYING
audlib/samples/arctic_a0001.wav
audlib/samples/welcome16k.wav
audlib/sig/__init__.py
audlib/sig/auditory.py
audlib/sig/callables.py
audlib/sig/cepstral.py
audlib/sig/fbanks.py
audlib/sig/phase.py
audlib/sig/spectemp.py
audlib/sig/spectral.py
audlib/sig/stproc.py
audlib/sig/temporal.py
audlib/sig/transform.py
audlib/sig/util.py
audlib/sig/window.py
audlib/tools/sph2pipe/bitshift.h
audlib/tools/sph2pipe/file_headers.c
audlib/tools/sph2pipe/shorten_x.c
audlib/tools/sph2pipe/sph2pipe.c
audlib/tools/sph2pipe/sph2pipe.exe
audlib/tools/sph2pipe/sph_convert.h
audlib/tools/sph2pipe/ulaw.h
audlib-0.0.3.5.dist-info/LICENSE
audlib-0.0.3.5.dist-info/METADATA
audlib-0.0.3.5.dist-info/WHEEL
audlib-0.0.3.5.dist-info/entry_points.txt
audlib-0.0.3.5.dist-info/top_level.txt
audlib-0.0.3.5.dist-info/RECORD
