Metadata-Version: 2.1
Name: audlib
Version: 0.0.3.5
Summary: A speech signal processing library with emphasis on deep learning.
Home-page: https://github.com/raymondxyy/pyaudlib
Author: Raymond Xia
Author-email: raymondxia@cmu.edu
License: MIT
Download-URL: https://github.com/raymondxyy/pyaudlib/archive/v_01.tar.gz
Keywords: SPEECH,AUDIO,SIGNAL,SOUND,DEEP LEARNING,NEURAL NETWORKS
Platform: UNKNOWN
Classifier: License :: OSI Approved :: MIT License
Classifier: Development Status :: 3 - Alpha
Classifier: Intended Audience :: Developers
Classifier: Topic :: Multimedia :: Sound/Audio :: Analysis
Classifier: Programming Language :: Python
Classifier: Programming Language :: Python :: 3
Classifier: Programming Language :: Python :: 3.6
Classifier: Programming Language :: Python :: 3.7
Requires-Dist: click (>=7.0)
Requires-Dist: numpy (>=1.17.2)
Requires-Dist: soundfile (>=0.10.2)
Requires-Dist: scipy (>=1.3.1)
Requires-Dist: resampy (>=0.2.2)
Provides-Extra: display
Requires-Dist: matplotlib (>=3.1.1) ; extra == 'display'
Provides-Extra: nn
Requires-Dist: torch (>=1.2.0) ; extra == 'nn'
Requires-Dist: torchvision (>=0.4.0) ; extra == 'nn'
Provides-Extra: tests
Requires-Dist: pytest (>=5.1.3) ; extra == 'tests'
Requires-Dist: pytest-cov (>=2.8.1) ; extra == 'tests'
Requires-Dist: codecov (>=2.0.15) ; extra == 'tests'
